{
  "Start with Template": {
    "message": "با قالب شروع کنید"
  },
  "scenes": {
    "message": "صحنهها"
  },
  "Tag Categories": {
    "message": "دستهبندیهایبرچسبها"
  },
  "Choose what categories you want to put your tags into": {
    "message": "انتخاب کنید که میخواهید برچسبهایتان را در چه دستهبندیهاییقرار دهید"
  },
  "(If not, please email support@plottr.com)": {
    "message": "(در غير اين صورت، لطفاً به support@plottr.com ايميل بزنيد)"
  },
  "(Logout)": {
    "message": "(خروج)"
  },
  "A verification code was sent to:": {
    "message": "يک کد تأييد ارسال شد به:"
  },
  "About Plottr": {
    "message": "درباره پلاتر"
  },
  "Access to all the features": {
    "message": "دسترسي به همه ويژگيها"
  },
  "Account Information": {
    "message": "اطلاعات حساب"
  },
  "Account": {
    "message": "حساب"
  },
  "Actions": {
    "message": "اقدامات"
  },
  "Activate License": {
    "message": "فعالسازي مجوز"
  },
  "Add Chapter": {
    "message": "افزودن فصل"
  },
  "Add attribute": {
    "message": "افزودن ويژگي"
  },
  "Add cards to the timeline so you can write notes about your scenes. Click on the card to add more details": {
    "message": "کارتهايي به تايم لاين اضافه کنيد تا بتوانيد نکاتي درباره صحنه هاي خود بنويسيد. براي افزودن جزئيات بيشتر، روي کارت کليک کنيد"
  },
  "Add category": {
    "message": "افزودن مقوله"
  },
  "Add more plotlines here": {
    "message": "در اينجا خطوط داستان بيشتري اضافه کنيد"
  },
  "Add new scenes or chapters here": {
    "message": "در اينجا صحنه ها يا فصلهاي جديد اضافه کنيد"
  },
  "Add": {
    "message": "افزودن"
  },
  "General": {
    "message": "پیشرفته"
  },
  "Title Page": {
    "message": "صفحه عنوان"
  },
  "Tags / Characters / Places": {
    "message": "برچسبها / شخصیتها / مکانها"
  },
  "Templates": {
    "message": "قالبها"
  },
  "Main plot": {
    "message": "طرح اصلی"
  },
  "Character Image": {
    "message": "تصویر شخصیت"
  },
  "Save these settings across projects?": {
    "message": "این تنظیمات در همه پروژهها ذخیره شود؟"
  },
  "Advanced...": {
    "message": "یشرفته"
  },
  "Advanced Export Options": {
    "message": "گزينه هاي پيشرفته صدور"
  },
  "After": {
    "message": "بعد از"
  },
  "All": {
    "message": "همه"
  },
  "App Version: {version}": {
    "message": "نسخه برنامه: {version}"
  },
  "Are you sure you want to clear everything in this timeline?": {
    "message": "واقعاً مي خواهيد همه چيز را در اين تايم لاين پاک کنيد؟"
  },
  "Are you sure you want to delete { thing }?": {
    "message": "آيا واقعا مي خواهيد { thing } را حذف کنيد؟"
  },
  "Are you sure you want to delete {name}?": {
    "message": "آيا واقعاً مي خواهيد \"{ name }\" را حذف کنيد؟"
  },
  "Are you sure you want to remove your license?": {
    "message": "واقعاً مي خواهيد مجوز خود را حذف کنيد؟"
  },
  "Are you sure?  (Removing levels may delete scene cards!)": {
    "message": "مطمئن هستيد؟  (حذف مراحل ممکن است کارتهاي صحنه را حذف کند!)"
  },
  "Attach Books": {
    "message": "الحاق کتابها"
  },
  "Attach Characters": {
    "message": "الحاق شخصيت ها"
  },
  "Attach Places": {
    "message": "الحاق مکانها"
  },
  "Attach Tags": {
    "message": "الحاق برچسب ها"
  },
  "Attributes": {
    "message": "ويژگيها"
  },
  "Auto-save": {
    "message": "ذخيره خودکار"
  },
  "Auto-saving failed": {
    "message": "ذخيره خودکار انجام نشد"
  },
  "Auto-saving worked": {
    "message": "ذخيره خودکار انجام شد"
  },
  "Automatically save daily backups": {
    "message": "پشتيبان هاي روزانه به طور خودکار ذخيره شود"
  },
  "Awesome choice!": {
    "message": "چه انتخاب خوبي!"
  },
  "Back": {
    "message": "بازگشت"
  },
  "Backup Location": {
    "message": "محل پشتيبان"
  },
  "Backups older than this will be erased": {
    "message": "پشتيبان هاي قديمي تر از اين حذف خواهند شد"
  },
  "Backups": {
    "message": "نسخه‌های پشتیبان شما"
  },
  "Beat 1": {
    "message": "خط سير 1"
  },
  "Beat {number} title": {
    "message": "عنوان {number} خط سير"
  },
  "Beat {number}": {
    "message": "خط سير {number}"
  },
  "Beat": {
    "message": "خط سير"
  },
  "Before": {
    "message": "قبل"
  },
  "Beginning": {
    "message": "شروع"
  },
  "Blues": {
    "message": "آبي ها"
  },
  "Book #": {
    "message": "کتاب #"
  },
  "Book Details": {
    "message": "جزئيات کتاب"
  },
  "Book": {
    "message": "کتاب"
  },
  "Books": {
    "message": "کتابها"
  },
  "Browns": {
    "message": "قهوه‌اي ها"
  },
  "Buy Full Version": {
    "message": "خريد نسخه کامل"
  },
  "By default, use auto-save for projects": {
    "message": "به طور پيشفرض از ذخيره خودکار براي پروژه ها استفاده شود"
  },
  "By starting a mobile subscription, you agree to Plottr's": {
    "message": "با شروع اشتراک موبايل، با شرايط پلاتر موافقت مي کنيد"
  },
  "CHECK EMAIL": {
    "message": "بررسي ايميل"
  },
  "CHECKING...": {
    "message": "در حال بررسي..."
  },
  "CODE": {
    "message": "CODE"
  },
  "CREATE NEW PROJECT": {
    "message": "ايجاد پروژه جديد"
  },
  "CREATE PROJECT": {
    "message": "ايجاد پروژه"
  },
  "Can I have a few more days?": {
    "message": "مي توانم چند روز ديگر داشته باشم؟"
  },
  "Cancel": {
    "message": "لغو"
  },
  "Card": {
    "message": "کارت"
  },
  "Categories": {
    "message": "دسته‌بندي‌ها"
  },
  "Category": {
    "message": "دسته‌بندي"
  },
  "Changelog": {
    "message": "گزارش تغييرات"
  },
  "Chapter {number} title": {
    "message": "عنوان {number} فصل"
  },
  "Chapter {number}": {
    "message": "فصل {number}"
  },
  "Chapter": {
    "message": "فصل"
  },
  "Chapters": {
    "message": "فصلها"
  },
  "Character Categories": {
    "message": "دسته‌بندي‌هاي شخصيت‌ها"
  },
  "Character Thumbnail": {
    "message": "تصوير کوچک شخصيت"
  },
  "Character list is filtered": {
    "message": "فهرست شخصيت‌ها فيلتر شده"
  },
  "Character": {
    "message": "شخصيت"
  },
  "Character: {name}": {
    "message": "شخصيت: {name}"
  },
  "Characters list": {
    "message": "فهرست شخصيت‌ها"
  },
  "Characters": {
    "message": "شخصيت‌ها"
  },
  "characters": {
    "message": "شخصيت‌ها"
  },
  "Check for Updates": {
    "message": "بررسي به‌روزرساني‌ها"
  },
  "Check": {
    "message": "بررسي"
  },
  "Choose Color": {
    "message": "انتخاب رنگ"
  },
  "Choose an image": {
    "message": "انتخاب تصوير"
  },
  "Choose an {platform} mobile subscription": {
    "message": "انتخاب يک {platform} اشتراک موبايل"
  },
  "Choose what categories you want to put your characters into": {
    "message": "انتخاب کنيد شخصيت خود را در چه دسته‌بندي‌هايي مي‌خواهيد قرار دهيد"
  },
  "Choose what you want to track about your { type }": {
    "message": "انتخاب کنيد چه چيز را مي خواهيد درباره {type} خود ردگيري کنيد"
  },
  "Choose where to save this file on your computer": {
    "message": "انتخاب کنيد اين فايل در کجاي کامپيوترتان ذخيره شود"
  },
  "Choose your Snowflake Pro file": {
    "message": "فايل اسنوفليک پرو خود را انتخاب کنيد"
  },
  "Choose": {
    "message": "انتخاب"
  },
  "Choose...": {
    "message": "انتخاب..."
  },
  "Clear": {
    "message": "پاک کردن"
  },
  "Click on a color below or type it in": {
    "message": "روي رنگ زير کليک کنيد يا آن را تايپ کنيد"
  },
  "Click to Install": {
    "message": "براي نصب کليک کنيد"
  },
  "Close": {
    "message": "بستن"
  },
  "Collapse": {
    "message": "باز کردن"
  },
  "Color Picker": {
    "message": "انتخاب رنگ"
  },
  "Color": {
    "message": "رنگ"
  },
  "Coming Soon!": {
    "message": "به زودي!"
  },
  "Configuration Options": {
    "message": "گزينه‌هاي پيکربندي"
  },
  "Configure": {
    "message": "پيکربندي"
  },
  "Content": {
    "message": "مطالب"
  },
  "Copy": {
    "message": "کپي"
  },
  "Create Blank Project": {
    "message": "ايجاد پروژه خالي"
  },
  "Create From Template": {
    "message": "ايجاد از الگوها"
  },
  "Create Report": {
    "message": "ايجاد گزارش"
  },
  "Create a New Plottr Document": {
    "message": "ايجاد يک سند جديد پلاتر"
  },
  "Create an Error Report": {
    "message": "ايجاد يک گزارش خطا"
  },
  "Create unlimited project files": {
    "message": "ايجاد فايلهاي نامحدود پروژه"
  },
  "Create": {
    "message": "ايجاد"
  },
  "Created By": {
    "message": "ايجاد شده توسط"
  },
  "Current Color": {
    "message": "رنگ کنوني"
  },
  "Custom Attributes for { type }": {
    "message": "ويژگي‌هاي سفارشي براي { type }"
  },
  "Custom Attributes": {
    "message": "ويژگيهاي سفارشي"
  },
  "Custom Template": {
    "message": "الگوي سفارشي"
  },
  "Custom Templates": {
    "message": "الگوهاي سفارشي"
  },
  "Cut": {
    "message": "برش"
  },
  "Delete": {
    "message": "حذف"
  },
  "Dark Mode": {
    "message": "حالت تيره"
  },
  "Dashboard": {
    "message": "داشبورد"
  },
  "Days Left": {
    "message": "روز باقيمانده"
  },
  "Days of Backup": {
    "message": "روز پشتيبان"
  },
  "Number of Backups": {
    "message": "تعداد پشتيبان ها"
  },
  "Never Delete Backups": {
    "message": "هرگز پشتيبان ها حذف نشود"
  },
  "Default Colors": {
    "message": "رنگهاي پيشفرض"
  },
  "Delete Chapter {name}?": {
    "message": "حذف فصل \"{name}\"?"
  },
  "Delete Chapter": {
    "message": "حذف فصل"
  },
  "Delete Character": {
    "message": "حذف شخصيت ها"
  },
  "Delete Plotline {name}?": {
    "message": "حذف خط طرح \"{name}\"؟"
  },
  "Delete Plotline": {
    "message": "حذف خط طرح"
  },
  "Delete Scene {name}?": {
    "message": "حذف صحنه \"{name}\"؟"
  },
  "Delete Scene": {
    "message": "حذف صحنه"
  },
  "Delete Tag": {
    "message": "حذف برچسب"
  },
  "Delete {title} Tag?": {
    "message": "حذف برچسب \"{title}\"؟"
  },
  "Demos": {
    "message": "پيش‌نمايش‌ها"
  },
  "Describe the scene": {
    "message": "شرح صحنه"
  },
  "Description": {
    "message": "شرح"
  },
  "Details": {
    "message": "جزئيات"
  },
  "Device ID": {
    "message": "شناسه دستگاه"
  },
  "Do you want to remove this image? It will NOT be deleted from your computer": {
    "message": "مي‌خواهيد اين تصوير را حذف کنيد؟ از روي کامپيوترتان حذف نخواهد شد"
  },
  "Documentation": {
    "message": "سند"
  },
  "Don't have a license? Go to our website to learn more": {
    "message": "مجوز نداريد؟ به وبسايت ما برويد و اطلاعات بيشتر کسب کنيد"
  },
  "Don't have a license?": {
    "message": "مجوز نداريد؟"
  },
  "Don't worry, all your work is saved in plottr_trial.pltr in your Documents folder": {
    "message": "نگران نباشيد، همه کارهايتان در پوشه اسنادتان در plottr_trial.pltr ذخيره شده است"
  },
  "Don't worry, all your work is saved in your files": {
    "message": "نگران نباشيد، همه کارتان در فايلهاي شما ذخيره شده است"
  },
  "Done": {
    "message": "انجام شد"
  },
  "Download Complete ًںژ‰ (version {version})": {
    "message": "دانلود کامل شد ًںژ‰ (نسخه { version })"
  },
  "Download Now!": {
    "message": "اکنون دانلود کنيد!"
  },
  "Download updates automatically": {
    "message": "دانلود به طور خودکار به روز مي شود"
  },
  "Downloading version {version}": {
    "message": "در حال دانلود نسخه { version }"
  },
  "Drop a File Here": {
    "message": "يک فايل در اينجا بيندازيد"
  },
  "Edit Plotline": {
    "message": "ويرايش خط طرح"
  },
  "Edit": {
    "message": "ويرايش"
  },
  "Email": {
    "message": "ايميل"
  },
  "Email:": {
    "message": "ايميل:"
  },
  "End": {
    "message": "پايان"
  },
  "Ends After": {
    "message": "پايان پس از"
  },
  "Enter Chapter's name or enter": {
    "message": "نام فصل را وارد کنيد يا براي نامگذاري خودکار \"auto\" \n(بدون گيومه) را وارد کنيد."
  },
  "Enter Custom Attribute Title": {
    "message": "عنوان ويژگي سفارشي را وارد کنيد"
  },
  "Enter a Customer Service Code": {
    "message": "يک کد خدمات مشتريان وارد کنيد"
  },
  "Enter a new name for {chapter}": {
    "message": "يک نام جديد وارد کنيد براي \"{chapter}\""
  },
  "Enter some text...": {
    "message": "مقداري متن وارد کنيد..."
  },
  "Enter the URL of the link:": {
    "message": "نشاني پيوند را وارد کنيد:"
  },
  "Enter the name of your project": {
    "message": "نام پروژه خود را وارد کنيد"
  },
  "Enter your verification code to activate this device": {
    "message": "کد تأييدتان را براي فعالسازي اين دستگاه وارد کنيد"
  },
  "Enter your verification code": {
    "message": "کد تأييدتان را وارد کنيد"
  },
  "Error Creating Error Report": {
    "message": "خطا حين ايجاد گزارش خطا"
  },
  "Error Report created": {
    "message": "گزارش خطا ايجاد شد"
  },
  "Error reading file": {
    "message": "خطا در خواندن فايل"
  },
  "Error sending email! Check your email and Try again.": {
    "message": "خطا در ارسال ايميل! ايميل خود را بررسي و دوباره تلاش کنيد."
  },
  "Error: {error}": {
    "message": "خطا: { error }"
  },
  "Exit Without Saving": {
    "message": "خروج بدون ذخيره"
  },
  "Expand": {
    "message": "گسترش"
  },
  "Expires": {
    "message": "منقضي مي شود"
  },
  "Export": {
    "message": "صدور"
  },
  "FAQ": {
    "message": "سؤالات متداول"
  },
  "Facebook Group": {
    "message": "گروه فيسبوکي"
  },
  "Fictional Devices LLC": {
    "message": "Fictional Devices LLC"
  },
  "File Exported": {
    "message": "فايل صادر شد"
  },
  "File can't be found. Did it move?": {
    "message": "فايل يافت نمي شود. جابجا شده؟"
  },
  "File": {
    "message": "فايل"
  },
  "Files": {
    "message": "فايلها"
  },
  "Filter by Plotline": {
    "message": "فيلتر طبق خط طرح"
  },
  "Filter": {
    "message": "فيلتر"
  },
  "Flip": {
    "message": "برگرداندن"
  },
  "Folder where backups are stored": {
    "message": "پوشه محل ذخيره نسخه هاي پشتيبان"
  },
  "Force Dark Mode": {
    "message": "حالت تيره اجباري"
  },
  "Free Trial Information": {
    "message": "اطلاعات آزمايش رايگان"
  },
  "Free Trial": {
    "message": "آزمايش رايگان"
  },
  "GET A LICENSE": {
    "message": "يک مجوز بگيريد"
  },
  "Get a License": {
    "message": "يک مجوز بگيريد"
  },
  "GET STARTED!": {
    "message": "شروع کنيد!"
  },
  "Genre": {
    "message": "ژانر"
  },
  "Get access to all your projects": {
    "message": "به همه پروژه‌هاي خود دسترسي بيابيد"
  },
  "Links": {
    "message": "پيوندها"
  },
  "Give this tag a name": {
    "message": "براي اين برچسب اسم بگذاريد"
  },
  "Give your scene a title": {
    "message": "براي صحنه خود اسم بگذاريد"
  },
  "Go Back": {
    "message": "بازگشت"
  },
  "Go to our website to learn more:": {
    "message": "براي کسب اطلاعات بيشتر به وبسايت ما مراجعه کنيد:"
  },
  "Grays": {
    "message": "خاکستري‌ها"
  },
  "Greens": {
    "message": "سبزها"
  },
  "Help": {
    "message": "راهنما"
  },
  "Hide Others": {
    "message": "مخفي کردن ديگران"
  },
  "Hide Plottr": {
    "message": "مخفي کردن پلاتر"
  },
  "Hierarchy Configuration": {
    "message": "پيکربندي سلسله مراتب"
  },
  "Hmmmm. It looks like that's not a valid license key": {
    "message": "هوم، انگار اين کليد مجوز معتبر نيست"
  },
  "I have a license key": {
    "message": "من يک کليد مجوز دارم"
  },
  "I want to buy the full version!": {
    "message": "مي خواهم نسخه کامل را بخرم!"
  },
  "I want to start the free trial": {
    "message": "مي خواهم آزمايش رايگان را شروع کنم"
  },
  "If you keep seeing this problem, email us at support@plottr.com": {
    "message": "اگر باز هم با اين مشکل مواجه شديد، با نشاني زير به ما ايميل بزنيد support@plottr.com"
  },
  "Image Details": {
    "message": "جزئيات تصوير"
  },
  "Image Gallery": {
    "message": "گالري تصاوير"
  },
  "Images": {
    "message": "تصاوير"
  },
  "Import Snowflake Pro": {
    "message": "وارد کردن اسنوفليک پرو"
  },
  "Insert Chapter and a Card": {
    "message": "درج فصل و يک کارت"
  },
  "Insert Chapter": {
    "message": "درج فصل"
  },
  "Insert from URL": {
    "message": "درج از نشاني اينترنتي"
  },
  "It looks like you have Plottr on the max number of computers already": {
    "message": "به نظر مي‌رسد در حال حاضر پلاتر را روي حداکثر تعداد کامپيوترها نصب کرده‌ايد"
  },
  "It looks like you have Plottr on the max number of devices already": {
    "message": "به نظر مي‌رسد در حال حاضر پلاتر را روي حداکثر تعداد دستگاه‌ها داريد"
  },
  "It looks like you're not online. You don't always have to be online to user Plottr, but it can't verify your license offline": {
    "message": "ظاهراً آنلاين نيستيد. لازم نيست براي استفاده از پلاتر هميشه آنلاين باشيد، اما نمي تواند مجوز شما را به صورت آفلاين تأييد کند"
  },
  "Keep all your notes here (brainstorming, world-building, etc.)": {
    "message": "همه يادداشت‌هاي خود را اينجا نگه داريد( طوفان مغزي، دنياسازي، و غيره)"
  },
  "Keep info about your locations here": {
    "message": "اطلاعات مربوط به مکان‌هاي خود را در اينجا نگه داريد"
  },
  "Keep your character sheets here": {
    "message": "صفحه‌هاي شخصيت‌هاي خود را در اينجا نگه داريد"
  },
  "LOGOUT": {
    "message": "خروج از سيستم"
  },
  "LOOK OUT!": {
    "message": "مراقب باشيد!"
  },
  "Language": {
    "message": "زبان"
  },
  "Last opened by you": {
    "message": "آخرين باري که توسط شما باز شده"
  },
  "Learn": {
    "message": "يادگيري"
  },
  "Let's verify your license.": {
    "message": "بياييد مجوزتان را تأييد کنيم."
  },
  "Levels of hierarchy": {
    "message": "سطوح سلسله مراتب"
  },
  "License Key": {
    "message": "کليد مجوز"
  },
  "License Verified. Plottr will start momentarily. Thanks for being patient!": {
    "message": "مجوز تأييد شد. پلاتر براي چند لحظه راه‌اندازي مي‌شود. از صبوري شما سپاسگزاريم!"
  },
  "License": {
    "message": "مجوز"
  },
  "Long Synopsis": {
    "message": "چکيده بلند"
  },
  "MS Word": {
    "message": "MS Word"
  },
  "Clear Timeline": {
    "message": "پاک کردن خط زمان"
  },
  "Guided tours": {
    "message": "تورهایهدایتشده"
  },
  "Act structure": {
    "message": "ساختار پرده"
  },
  "none": {
    "message": "یچکدام"
  },
  "dashed": {
    "message": "خطچین"
  },
  "solid": {
    "message": "یکدست"
  },
  "dotted": {
    "message": "نقطهچین"
  },
  "Background Color": {
    "message": "رنگ پسزمینه"
  },
  "Border Style": {
    "message": "سبک حاشیه"
  },
  "Border Color": {
    "message": "رنگ حاشیه"
  },
  "Text Size": {
    "message": "اندازه متن"
  },
  "Text Color": {
    "message": "رنگ متن"
  },
  "Main Plot": {
    "message": "طرح اصلي"
  },
  "Main": {
    "message": "اصلي"
  },
  "Manually Sorted": {
    "message": "به صورت دستي ذخيره شده"
  },
  "Manuscript": {
    "message": "دستنويس"
  },
  "Menu": {
    "message": "منو"
  },
  "Middle": {
    "message": "ميانه"
  },
  "My Character Template": {
    "message": "الگوي شخصيت‌هاي من"
  },
  "My Scene Template": {
    "message": "الگوي صحنه‌هاي من"
  },
  "My Templates": {
    "message": "الگوهاي من"
  },
  "My Timeline Template": {
    "message": "الگوي تايم لاين من"
  },
  "Name": {
    "message": "نام"
  },
  "Never": {
    "message": "هرگز"
  },
  "New Attribute": {
    "message": "ويژگي جديد"
  },
  "New Book": {
    "message": "کتاب جديد"
  },
  "New Character": {
    "message": "شخصيت جديد"
  },
  "New Custom Attribute Title": {
    "message": "عنوان ويژگي سفارشي جديد"
  },
  "New Note": {
    "message": "يادداشت جديد"
  },
  "New Place": {
    "message": "مکان جديد"
  },
  "New Plotline": {
    "message": "خط طرح جديد"
  },
  "New Project": {
    "message": "پروژه جديد"
  },
  "New Tag": {
    "message": "برچسب جديد"
  },
  "New": {
    "message": "جديد"
  },
  "No Characters": {
    "message": "بدون شخصيت"
  },
  "No actions to undo": {
    "message": "عملي براي لغو وجود ندارد"
  },
  "No color": {
    "message": "بدون رنگ"
  },
  "No": {
    "message": "خير"
  },
  "No, Discard": {
    "message": "خير، دور انداخته شود"
  },
  "None to choose": {
    "message": "براي انتخاب وجود ندارد"
  },
  "Not Receiving Updates": {
    "message": "به‌روزرساني‌ها دريافت نمي‌شود"
  },
  "Note Details": {
    "message": "جزئيات يادداشت"
  },
  "Note Image": {
    "message": "تصوير يادداشت"
  },
  "Note": {
    "message": "يادداشت"
  },
  "Note: {title}": {
    "message": "يادداشت: {title}"
  },
  "Notes are filtered": {
    "message": "يادداشت‌ها فيلتر شده‌اند"
  },
  "Notes": {
    "message": "يادداشت‌ها"
  },
  "Now lets get you writing your next great plot!": {
    "message": "حالا بياييد برويم سراغ نوشتن\n طرح عالي بعدي‌تان!"
  },
  "Number of Days of Rolling Backups to Keep": {
    "message": "تعداد روزهای نگهداشتن نسخه‌های پشتیبان"
  },
  "OK": {
    "message": "تأييد"
  },
  "OVERWRITE": {
    "message": "رونویسی"
  },
  "Once You Plot, the Fun Don't Stop": {
    "message": "وقتي طرح‌نويسي کنيد، لذتش تمام‌نشدني است"
  },
  "One Paragraph Summary": {
    "message": "خلاصه يک‌پاراگرافي"
  },
  "One Sentence Summary": {
    "message": "خلاصه يک‌جمله‌اي"
  },
  "Open Dashboard": {
    "message": "باز کردن داشبورد"
  },
  "Open Existing": {
    "message": "باز کردن موجود"
  },
  "Open Existing File": {
    "message": "باز کردن فایل موجود"
  },
  "Open a Plottr Document": {
    "message": "باز کردن يک سند پلاتر"
  },
  "Open one of your most recent projects": {
    "message": "باز کردن يکي از جديدترين پروژه‌هايتان"
  },
  "Open": {
    "message": "باز کردن"
  },
  "Or hover here to insert between scenes": {
    "message": "یا اینجا مکث کنید تا بین صحنه‌ها وارد شود"
  },
  "Oranges": {
    "message": "نارنجی‌ها"
  },
  "Other": {
    "message": "سایر"
  },
  "Outline is filtered": {
    "message": "طرح فیلتر شده است"
  },
  "Outline": {
    "message": "طرح"
  },
  "Override your computer's setting and always use dark mode": {
    "message": "لغو تنظیمات کامپیوتر شما و استفاده دائمی از حالت تاریک"
  },
  "Paragraph": {
    "message": "بند"
  },
  "Paragraph?": {
    "message": "بند؟"
  },
  "Paste and Match Style": {
    "message": "چسباندن و تطبیق سبک"
  },
  "Paste": {
    "message": "چسباندن"
  },
  "Pick a color": {
    "message": "انتخاب یک رنگ"
  },
  "Place Details": {
    "message": "قرار دادن جزئیات"
  },
  "Place Image": {
    "message": "قرار دادن تصویر"
  },
  "Place list is filtered": {
    "message": "لیست مکان‌ها فیلتر شده"
  },
  "Place": {
    "message": "مکان"
  },
  "Place: {name}": {
    "message": "مکان: { name }"
  },
  "Places list": {
    "message": "فهرست مکان‌ها"
  },
  "Places": {
    "message": "مکان‌ها"
  },
  "Please choose a plotline": {
    "message": "لطفً یک خط طری انتخاب کنید"
  },
  "Please contact us with any questions at support@plottr.com": {
    "message": "لطفاً هر سوالی دارید با نشانی زیر با من تماس بگیرید support@plottr.com"
  },
  "Please select a valid Plottr file": {
    "message": "لطفاً یک فایل معتبر پلاتر انتخاب کنید."
  },
  "Please verify your license": {
    "message": "لطفاً مجوز خود را تأیید کنید"
  },
  "Plotline Details": {
    "message": "جزئیات خط طرح"
  },
  "Plotline Title:": {
    "message": "عنوان خط طرح:"
  },
  "Plotline name": {
    "message": "نام خط طرح"
  },
  "Plotline": {
    "message": "خط طرح"
  },
  "Plotline: {title}": {
    "message": "خط طرح: { title }"
  },
  "Plotlines": {
    "message": "خطوط داستان"
  },
  "Plottr Mobile Monthly": {
    "message": "پلاتر موبایل ماهانه"
  },
  "Plottr Mobile Yearly": {
    "message": "پلاتر موبایل سالانه"
  },
  "Plottr Mobile": {
    "message": "پلاتر موبایل"
  },
  "Plottr Support": {
    "message": "پشتیبانی پلاتر"
  },
  "Plottr created a file named {fileName} in your Documents folder": {
    "message": "پلاتر فایلی با نام { fileName } در پوشه اسناد شما ایجاد کرد"
  },
  "Plottr project file": {
    "message": "فایل پروژه پلاتر"
  },
  "Plottr ran into a problem. Try opening Plottr again.": {
    "message": "پلاتر دچار مشکل شد. سعی کنید دوباره آن را باز کنید."
  },
  "Plottr": {
    "message": "پلاتر"
  },
  "Preferences": {
    "message": "ترجیحات"
  },
  "Premise": {
    "message": "مبنا"
  },
  "Privacy Policy": {
    "message": "خط مشی حریم خصوصی"
  },
  "Project Templates": {
    "message": "قالب های پروژه"
  },
  "Project": {
    "message": "پروژه"
  },
  "Prologue": {
    "message": "مقدمه"
  },
  "Purchase Email": {
    "message": "ایمیل خرید"
  },
  "Purples": {
    "message": "زرشکی"
  },
  "Quit": {
    "message": "خروج"
  },
  "RESEND EMAIL": {
    "message": "ارسال مجدد ایمیل"
  },
  "RESENDING...": {
    "message": "در حال ارسال مجدد..."
  },
  "Recent Projects": {
    "message": "پروژه‌های اخیر"
  },
  "Redo": {
    "message": "انجام مجدد"
  },
  "Reds": {
    "message": "قرمزها"
  },
  "Reload from File": {
    "message": "بارگذاری مجدد از فایل"
  },
  "Reload": {
    "message": "بارگذاری مجدد"
  },
  "Deactivate License Key": {
    "message": "حذف مجوز"
  },
  "Remove from this list": {
    "message": "حذف از این فهرست"
  },
  "Remove image": {
    "message": "حذف تصویر"
  },
  "Remove": {
    "message": "حذف"
  },
  "Rename Chapter": {
    "message": "نامگذاری مجدد فصل"
  },
  "Rename": {
    "message": "نامگذاری مجدد"
  },
  "Contact Support": {
    "message": "گزارش یک مشکل"
  },
  "Request a Feature": {
    "message": "درخواست یک ویژگی"
  },
  "Restore Purchase": {
    "message": "بازیابی خرید"
  },
  "Roadmap": {
    "message": "نقشه مسیر"
  },
  "SELECT A PROJECT FILE": {
    "message": "یک فایل پروژه انتخاب کنید"
  },
  "SELECT": {
    "message": "انتخاب"
  },
  "Save Backups": {
    "message": "ذخیره نسخه‌های پشتیبان"
  },
  "Save Changes?": {
    "message": "ذخیره تغییرات؟"
  },
  "Save Chapter": {
    "message": "ذخیره فصل"
  },
  "Save File": {
    "message": "ذخیره فایل"
  },
  "Save Plotline": {
    "message": "ذخیره خط داستان"
  },
  "Save as Template": {
    "message": "ذخیره به عنوان قالب"
  },
  "Save as": {
    "message": "ذخیره به عنوان"
  },
  "Save before closing?": {
    "message": "ذخیره قبل از بستن؟"
  },
  "Save": {
    "message": "ذخیره"
  },
  "Saved": {
    "message": "ذخیره شد"
  },
  "Saving failed": {
    "message": "ذخیره انجام نشد"
  },
  "Saving worked this time": {
    "message": "ذخیره این بار موفق بود"
  },
  "Saving your file didn't work. Check where it's stored.": {
    "message": "ذخیره فایل شما موفق نبود. بررسی کنید که کجا نگهداری می شود."
  },
  "Saving your file didn't work. Try again.": {
    "message": "ذخیره فایل شما موفق نبود. دوباره تلاش کنید."
  },
  "Scene Cards": {
    "message": "کارتهای صحنه"
  },
  "Scene Details": {
    "message": "جزئیات صحنه"
  },
  "Scene Title": {
    "message": "عنوان صحنه"
  },
  "Scene {num}": {
    "message": "صحنه { num }"
  },
  "Scene": {
    "message": "صحنه"
  },
  "Scrivener Project": {
    "message": "پروژۀ اسکریونر"
  },
  "Scrivener": {
    "message": "Scrivener"
  },
  "Scroll": {
    "message": "پیمایش"
  },
  "Search": {
    "message": "جستجو"
  },
  "See What's New": {
    "message": "مشاهده تازه‌ها"
  },
  "See the outline here": {
    "message": "طرح را اینجا ببینید"
  },
  "Select All": {
    "message": "انتخاب همه"
  },
  "Select a Category": {
    "message": "انتخاب یک دسته"
  },
  "Select a Chapter": {
    "message": "انتخاب یک فصل"
  },
  "Select a File": {
    "message": "انتخاب یک فایل"
  },
  "Select a Plotline": {
    "message": "انتخاب یک خط طرح"
  },
  "Series Outline": {
    "message": "طرح مجموعه"
  },
  "Series View": {
    "message": "مشاهده مجموعه"
  },
  "Series": {
    "message": "مجموعه"
  },
  "Session Start": {
    "message": "شروع جلسه"
  },
  "Settings": {
    "message": "تنظیمات"
  },
  "Short Description": {
    "message": "شرح مختصر"
  },
  "Short Synopsis": {
    "message": "چکیده کوتاه"
  },
  "Show All": {
    "message": "نمایش همه"
  },
  "Show in File Explorer": {
    "message": "نمایش در مرورگر فایل"
  },
  "Show in Finder": {
    "message": "نمایش در جستجوگر"
  },
  "Since this is your first time using Plottr, I'll give you a guided tour if you like.": {
    "message": "چون نخستین بار است که از پلاتر استفاده می کنید، اگر مایلید یک تور راهنما برگزار کنیم."
  },
  "Size: large": {
    "message": "اندازه: بزرگ"
  },
  "Size: medium": {
    "message": "اندازه: متوسط"
  },
  "Size: small": {
    "message": "اندازه: کوچک"
  },
  "Something went wrong,": {
    "message": "اشکالی پیش آمد،"
  },
  "Something went wrong.": {
    "message": "اشکالی پیش آمد."
  },
  "Sort": {
    "message": "مرتب‌سازی"
  },
  "Source Link": {
    "message": "پیوند منبع"
  },
  "Start Mobile Subscription": {
    "message": "شروع اشتراک موبایل"
  },
  "Start my Free Trial": {
    "message": "شروع آزمایش رایگان من"
  },
  "Started On": {
    "message": "شروع از"
  },
  "Starter Templates": {
    "message": "قالبهای راه‌انداز"
  },
  "Story line": {
    "message": "خط داستان"
  },
  "Story name": {
    "message": "نام داستان"
  },
  "Submit": {
    "message": "ارسال"
  },
  "Subscription Restored!": {
    "message": "اشتراک بازیابی شد!"
  },
  "Subtitle": {
    "message": "عنوان فرعی"
  },
  "Success!": {
    "message": "موفق!"
  },
  "Supporting": {
    "message": "پشتیبان"
  },
  "Tag Details": {
    "message": "جزئیات برچسب"
  },
  "Tag Name": {
    "message": "نام برچسب"
  },
  "Tag": {
    "message": "برچسب"
  },
  "Tags can be used for organization": {
    "message": "برچسبها را می‌توان برای سازمان‌دهی به کار برد"
  },
  "Tags list": {
    "message": "فهرست برچسب‌ها"
  },
  "Tags": {
    "message": "برچسب‌ها"
  },
  "Take Screenshot": {
    "message": "گرفتن عکس از صفحه"
  },
  "Template Saved": {
    "message": "قالب ذخیره شد"
  },
  "Terms of Service": {
    "message": "شرایط خدمات"
  },
  "Text Error": {
    "message": "خطای متن"
  },
  "Thanks for trying Plottr": {
    "message": "از اینکه پلاتر را امتحان کردید متشکریم"
  },
  "That code was invalid. Try again.": {
    "message": "آن کد نامعتبر بود.\nدوباره تلاش کنید."
  },
  "That email didn't verify. Try again or try another email.": {
    "message": "آن ایمیل تأیید نشد.\nدوباره تلاش کنید یا ایمیل دیگری را امتحان کنید."
  },
  "Theme": {
    "message": "تِم"
  },
  "There was an error activating your license key on this device": {
    "message": "خطایی در فعالسازی کلید مجوز شما روی این دستگاه پیش آمد"
  },
  "There was an error doing that. Try again": {
    "message": "خطایی در انجام این کار پیش آمد. دوباره امتحان کنید."
  },
  "This is a plotline": {
    "message": "این یک خط طرح است"
  },
  "This is a scene or chapter. You can change its name by clicking on it": {
    "message": "این یک صحنه یا فصل است. می توانید نام آن را را کلیک کردن روی آن تغییر دهید"
  },
  "This will send you an email with a code": {
    "message": "این یک ایمیل با یک کد برای شما ارسال خواهد کرد"
  },
  "Timeline is filtered": {
    "message": "خط زمان فیلتر شده است"
  },
  "Timeline": {
    "message": "خط زمان"
  },
  "Title": {
    "message": "عنوان"
  },
  "Toggle navigation": {
    "message": "تغییر مرور"
  },
  "Trash": {
    "message": "زباله"
  },
  "Try that again": {
    "message": "دوباره آن را امتحان کن"
  },
  "Tutorials": {
    "message": "آموزش‌ها"
  },
  "Type": {
    "message": "نوع"
  },
  "UH-OH!": {
    "message": "ای وای!"
  },
  "URL": {
    "message": "نشانی اینترنتی"
  },
  "Uncategorized": {
    "message": "دسته‌بندی نشده"
  },
  "Undo": {
    "message": "لغو انجام"
  },
  "auto": {
    "message": "خودکار"
  },
  "Remove template": {
    "message": "حذف قالب"
  },
  "Untitled": {
    "message": "بدون عنوان"
  },
  "untitled": {
    "message": "بدون عنوان"
  },
  "Update Automatically": {
    "message": "به‌روزرسانی خودکار"
  },
  "Update Available (version {version})": {
    "message": "به‌روزرسانی موجود است (نسخه { version })"
  },
  "Update failed. Try again": {
    "message": "به‌روزسانی انجام نشد. دوباره تلاش کنید"
  },
  "Updates": {
    "message": "به‌روزرسانی‌ها"
  },
  "Upload Files": {
    "message": "به‌روزرسانی فایل‌ها"
  },
  "Use Template": {
    "message": "استفاده از قالب"
  },
  "Use a different email": {
    "message": "استفاده از یک ایمیل دیگر"
  },
  "Use this to remove your license on this device": {
    "message": "با استفاده از این، مجوز خود روی این دستگاه را حذف کنید"
  },
  "VERIFY CODE": {
    "message": "تأیید کد"
  },
  "VERIFYING...": {
    "message": "در حال تأیید..."
  },
  "Verify": {
    "message": "تأیید"
  },
  "Verifying with email: {email}": {
    "message": "تأیید با ایمیل: { email }"
  },
  "Version": {
    "message": "نسخه"
  },
  "View Error": {
    "message": "مشاهده خطا"
  },
  "View Timeline": {
    "message": "مشاهده خط زمان"
  },
  "View": {
    "message": "مشاهده"
  },
  "We found your user session but...": {
    "message": "ما جلسه کاربری شما را یافتیم، اما مجوز شما لغو شده یا غیرفعال است. لطفاً یک مجوز جدید یا اشتراک موبایل تهیه کنید تا ادامه دهید."
  },
  "We had a problem creating a new project": {
    "message": "ما در ایجاد یک  پروژۀ جدید مشکل داشتیم. مطمئن شوید پلاتر مجوزهای صحیح را دارد و شما فضای کافی دارید."
  },
  "We had a problem processing your file": {
    "message": "ما در پردازش فایل شما مشکل داشتیم. مطمئن شوید پلاتر مجوزهای صحیح را دارد و دوباره تلاش کنید."
  },
  "We will email you a verification code.": {
    "message": "ما یک کد تأیید برای شما ایمیل می کنیم."
  },
  "Welcome to Plottr!": {
    "message": "به پلاتر خوش آمدید!"
  },
  "Welcome to Plottr": {
    "message": "به پلاتر خوش آمدید"
  },
  "Welcome to": {
    "message": "خوش آمدید به"
  },
  "What would you like to do?": {
    "message": "می‌خواهید چه کار کنید؟"
  },
  "Where would you like to save the export?": {
    "message": "مایلید محتوای صادر شده کجا ذخیره شود؟"
  },
  "Where would you like to save this copy?": {
    "message": "مایلید این نسخه را کجا ذخیره کنید؟"
  },
  "Where would you like to save this file?": {
    "message": "مایلید این فایل را کجا ذخیره کنید؟"
  },
  "Whites": {
    "message": "سفیدها"
  },
  "Window": {
    "message": "پنجره"
  },
  "Word Document": {
    "message": "سند وُرد"
  },
  "Yes, Delete": {
    "message": "بله حذف شود"
  },
  "Yes, Save": {
    "message": "بله، ذخیره شود"
  },
  "You already have a file named {file}": {
    "message": "شما از قبل فایلی به نام \n{file} دارید.\nمایلید روی آن نوشته شود؟"
  },
  "You can change its name or color by hovering over it (disabled for the tour)": {
    "message": "با مکث روی آن می‌توانید نام یا رنگش را عوض کنید (برای تور غیرفعال شده)"
  },
  "You can create an error report and report the problem to us at: ": {
    "message": "می‌توانید یک گزارش خطا ایجاد کنید و مشکل را به ما از طریق زیر گزارش دهید: "
  },
  "You can export everything to a Word document": {
    "message": "می‌توانید همه چیز را به یک سند وُرد صادر کنید"
  },
  "You can have 5 more days to try Plottr": {
    "message": "می‌توانید ۵ روز دیگر برای امتحان کردن پلاتر داشته باشید"
  },
  "You have unsaved changes": {
    "message": "تغییرات شما ذخیره نشده است..\nمایلید آنها را ذخیره کنید؟"
  },
  "You may create a new project": {
    "message": "می‌توانید یک پروژه جدید ایجاد کنید\nیا یک فایل پروژه را برای شروع انتخاب کنید"
  },
  "Your email didn't verify. Try again or try another email.": {
    "message": "ایمیل شما تأیید نشد.\nدوباره تلاش کنید یا ایمیل دیگری را امتحان کنید."
  },
  "Your selected license failed verification. Try another one.": {
    "message": "مجوز انتخاب شده شما تأیید نشد. مجوز دیگری را امتحان کنید."
  },
  "You should have received a license key after your purchase.": {
    "message": "باید کلید مجوز را پس از خرید خود دریافت کرده باشید."
  },
  "You should have received an email with a code": {
    "message": "باید ایمیلی همراه با یک کد دریافت کرده باشید."
  },
  "You'll have 30 days": {
    "message": "شما ۳۰ روز فرصت خواهید داشت"
  },
  "You're on the latest version": {
    "message": "شما در حال استفاده از آخرین نسخه هستید‌"
  },
  "Your Plottr file was exported to a .docx file": {
    "message": "فایل پلاتر شما به یک فایل .docx صادر شد"
  },
  "Your Plottr file was exported to a Scrivener project package": {
    "message": "فایل پلاتر شما به بسته پروژه اسکریونر صادر شد"
  },
  "Your free trial has expired": {
    "message": "آزمایش رایگان شما منقضی شد‌"
  },
  "Your template has been saved and is ready to use": {
    "message": "قالب شما ذخیره شد و آمادۀ استفاده است"
  },
  "Zoom": {
    "message": "زوم"
  },
  "[image]": {
    "message": "[تصویر]"
  },
  "[Blank]": {
    "message": "[خالی]"
  },
  "a lot of scenes moved around": {
    "message": "صحنه‌های زیادی جابجا شدند"
  },
  "a lot of story lines moved around": {
    "message": "خطوط قصه زیادی جابجا شدند"
  },
  "and": {
    "message": "و"
  },
  "attach character {characterName} to card {cardName}": {
    "message": "اتصال شخصیت { characterName } به کارت { cardName }"
  },
  "attach character {characterName} to note {noteName}": {
    "message": "اتصال شخصیت { characterName } به یادداشت { noteName }"
  },
  "attach place {placeName} to card {cardName}": {
    "message": "اتصال مکان { placeName } به کارت { cardName }"
  },
  "attach place {placeName} to note {noteName}": {
    "message": "اتصال مکان { placeName } به یادداشت { noteName }"
  },
  "attach tag {tagName} to card {cardName}": {
    "message": "اتصال برچسب { tagName } به کارت { cardName }"
  },
  "attach tag {tagName} to note {noteName}": {
    "message": "اتصال برچسب { tagName } به یادداشت { noteName }"
  },
  "blank": {
    "message": "خالی"
  },
  "but don't worry!": {
    "message": "اما نگران نباشید!"
  },
  "custom character attribute": {
    "message": "ویژگی سفارشی شخصیت"
  },
  "custom place attribute": {
    "message": "ویژگی سفارشی مکان"
  },
  "hex code or name": {
    "message": "نام یا کد هکس"
  },
  "new card": {
    "message": "کارت جدید"
  },
  "new scene": {
    "message": "صحنه جدید"
  },
  "new storyline": {
    "message": "خط داستان جدید"
  },
  "no more to add": {
    "message": "بیشتر اضافه نمی‌شود"
  },
  "or": {
    "message": "یا"
  },
  "remove character {characterName} from card {cardName}": {
    "message": "حذف شخصیت { characterName } از کارت { cardName }"
  },
  "remove character {characterName} from note {noteName}": {
    "message": "حذف شخصیت { characterName } از یادداشت { noteName }"
  },
  "remove place {placeName} from card {cardName}": {
    "message": "حذف مکان { placeName } از کارت { cardName }"
  },
  "remove place {placeName} from note {noteName}": {
    "message": "حذف مکان { placeName } از یادداشت { noteName }"
  },
  "remove tag {tagName} from card {cardName}": {
    "message": "حذف برچسب { tagName } از کارت { cardName }"
  },
  "remove tag {tagName} from note {noteName}": {
    "message": "حذف برچسب { tagName } از یادداشت { noteName }"
  },
  "that best suits your style and needs.": {
    "message": "که بهتر با سبک و نیازهای شما مطابقت دارد."
  },
  "to activate this device.": {
    "message": "برای فعال کردن این دستگاه."
  },
  "with an iOS mobile subscription!": {
    "message": "با اشتراک موبایل iOS!"
  },
  "{\n          count, plural,\n          one {1 character attached}\n          other {# characters attached}\n        }": {
    "message": "{ شمارش، جمع،\n    یک {1 شخصیت پیوست شده}\n  دیگر {# شخصیت پیوست شده}\n}"
  },
  "{\n          count, plural,\n          one {1 place attached}\n          other {# places attached}\n        }": {
    "message": "{ شمارش، جمع،\n    یک {1 مکان پیوست شده}\n  دیگر {# مکان پیوست شده}\n}"
  },
  "{\n          count, plural,\n          one {1 tag attached}\n          other {# tags attached}\n        }": {
    "message": "{ شمارش، جمع\n    یک {1 برچسب پیوست شده}\n  دیگر {# برچسب پیوست شده}\n}"
  },
  "{amount} Lifetime": {
    "message": "${amount}\nمادام‌العمر"
  },
  "{amount} Monthly": {
    "message": "${amount}\nماهانه"
  },
  "{amount} Weekly": {
    "message": "${amount}\nهفتگی"
  },
  "{amount} Yearly": {
    "message": "${amount}\nسالانه"
  },
  "{date, date, long}": {
    "message": "{ تاریخ، تاریخ، طولانی }"
  },
  "{date, date, medium}": {
    "message": "{ تاریخ، تاریخ، متوسط }"
  },
  "{date, date, monthDay}": {
    "message": "{ تاریخ، تاریخ، روز ماه }"
  },
  "{numOfDays, plural,\n      =0 {# days left}\n      one {# day left}\n      other {# days left}\n    }": {
    "message": "{ تعداد روزها، جمع،\n     =0 {# روز باقیمانده}\n    یک {# روز باقیمانده}\n  دیگر {# روز باقیمانده}\n}"
  },
  "{num} Scenes": {
    "message": "{num} صحنه"
  },
  "{val, number, percent}": {
    "message": "{ مقدار، عدد، درصد }"
  },
  "{wordCount,number} words": {
    "message": "{wordCount, number} کلمه"
  },
  "Add attributes": {
    "message": "افزودن ویژگی‌ها"
  },
  "Attached to": {
    "message": "پیوست شده به"
  },
  "Bring All to Front": {
    "message": "آوردن همه به جلو"
  },
  "Buy the Full Version": {
    "message": "خرید نسخه کامل"
  },
  "Card Title": {
    "message": "عنوان کارت"
  },
  "character": {
    "message": "شخصیت"
  },
  "Choose color": {
    "message": "انتخاب رنگ"
  },
  "Choose what you want to track about your characters": {
    "message": "انتخاب کنید چه چیزی را می‌خواهید دربارۀ شخصیت‌های خود دنبال کنید"
  },
  "Choose what you want to track about your places": {
    "message": "انتخاب کنید چه چیز را می‌خواهید دربارۀ مکان‌های خود دنبال کنید"
  },
  "Click here to get the full version": {
    "message": "برای دریافت نسخه کامل اینجا کلیک کنید"
  },
  "Contact": {
    "message": "تماس"
  },
  "Create a new file": {
    "message": "ایجاد یک فایل جدید"
  },
  "Creates a report to send me": {
    "message": "یک گزارش برای ارسال به من ایجاد می‌کند"
  },
  "Creating your file didn't work. Let's try again.": {
    "message": "ایجاد فایل شما موفق نبود. بیایید دوباره تلاش کنیم."
  },
  "Credits": {
    "message": "سازندگان"
  },
  "Custom Attributes for Characters": {
    "message": "ویژگی‌های سفارشی برای شخصیت‌ها"
  },
  "Custom Attributes for Places": {
    "message": "ویژگی‌های سفارشی برای مکان‌ها"
  },
  "Do you want to delete this card: { title }?": {
    "message": "مایلید این کارت را حذف کنید: { title }?"
  },
  "+ Add Template": {
    "message": "افزودن قالب"
  },
  "DELETE": {
    "message": "حذف"
  },
  "Do you want to delete this character: { character }?": {
    "message": "آیا مایلید این شخصیت را حذف کنید؟: { character }"
  },
  "Do you want to delete this note: { title }?": {
    "message": "آیا مایلید این یادداشت را حذف کنید؟: { title }"
  },
  "Do you want to delete this place: { name }?": {
    "message": "آیا مایلید این مکان را حذف کنید؟: { name }"
  },
  "Do you want to delete this scene: { title }?": {
    "message": "آیا مایلید این صحنه را حذف کنید: { title }؟"
  },
  "Do you want to delete this story line: { title }?": {
    "message": "آیا مایلید این خط داستان را حذف کنید: { title }؟"
  },
  "Do you want to delete this tag: { title }?": {
    "message": "آیا مایلید این برچسب را حذف کنید: { title }؟"
  },
  "Enter License": {
    "message": "مجوز را وارد کنید"
  },
  "Filter by story line": {
    "message": "فیلتر بر اساس خط داستان"
  },
  "Fit": {
    "message": "جا دادن"
  },
  "Format with markdown!": {
    "message": "قالب با کاهش قیمت!"
  },
  "Forums": {
    "message": "انجمن‌ها"
  },
  "Give feedback": {
    "message": "دادن بازخورد"
  },
  "If you keep seeing this problem, email me at support@plottr.com": {
    "message": "اگر باز هم این مشکل را دیدید، با نشانی زیر به من ایمیل بزنید support@plottr.com"
  },
  "It looks like you have Plottr on 5 computers already": {
    "message": "ظاهراً در حال حاضر پلاتر را روی ۵ کامپیوتر نصب کرده‌اید"
  },
  "It looks like you have an older file version. This could make things work funky or not at all. May Plottr update it for you?": {
    "message": "ظاهراً شما نسخه فایل قدیمی‌تری دارید. این ممکن است باعث ایجاد مشکل شود یا اصلاً کار نکند. مایلید پلاتر آن را برای شما به‌روزرسانی کند؟"
  },
  "It looks like your file was saved with a newer version of Plottr than you're using now. That could cause problems. Try updating Plottr and starting it again.": {
    "message": "ظاهراً فایل شما با نسخه جدیدتری از پلاتر ذخیره شده که از نسخه فعلی جدیدتر است. این ممکن است باعث ایجاد مشکل شود. سعی کنید پلاتر را به روز کنید و دوباره راه‌اندازی کنید."
  },
  "It will save a backup first which will be saved to the same folder as this file": {
    "message": "ابتدا یک نسخه پشتیبان ذخیره خواهد کرد که در همان پوشه این فایل ذخیره خواهد شد"
  },
  "License verification failed": {
    "message": "تأیید مجوز انجام نشد"
  },
  "License verified! You're all set.": {
    "message": "مجوز تأیید شد! همه چیز جور است."
  },
  "Line": {
    "message": "خط"
  },
  "Loading...": {
    "message": "در حال بارگذاری..."
  },
  "Minimize": {
    "message": "کوچک‌سازی"
  },
  "My awesome story": {
    "message": "داستان عالی من"
  },
  "Nope. Plottr tried again. But it didn't work. Plottr will ask you next time it opens, but you're verified. Enjoy": {
    "message": "خیر. پلاتر دوباره تلاش کرد. اما کار نمی‌کند. پلاتر دفعه بعد که باز می‌شود از شما درخواست خواهد کرد، اما تأیید شدید. لذت ببرید"
  },
  "Now let's get to the good stuff": {
    "message": "حالا بیایید برویم سراغ چیزهای خوب"
  },
  "Open the Tour": {
    "message": "تور را باز کنید"
  },
  "Or feel free to contact me with any questions": {
    "message": "یا با خیال راحت هر سؤالی دارید از من بپرسید"
  },
  "place": {
    "message": "مکان"
  },
  "Please upload the file named plottr_error_report.txt in your Documents folder": {
    "message": "لطفاً فایل موسوم به plottr_error_report.txt را که در پوشه اسناد شماست آپلود کنید"
  },
  "Plottr couldn't save a backup. It hasn't touched your file yet, so don't worry. Try quitting Plottr and starting it again.": {
    "message": "پلاتر نمی‌تواند یک نسخه پشتیبان ذخیره کند. هنوز فایل شما را دستکاری نکرده، بنابراین نگران نباشید. سعی کنید از پلاتر خارج شوید و دوباره آن را راه اندازی کنید.."
  },
  "Plottr saved a backup just in case and now on with the show (To use the backup, remove '.backup' from the file name)": {
    "message": "پلاتر فقط محض احتیاط یک نسخه پشتیبان ذخیره کرد (برای استفاده از نسخه پشتیبان، '.backup' را از نام فایل حذف کنید)"
  },
  "Plottr tried saving a backup just in case, but it didn't work. Try quitting Plottr and starting it again.": {
    "message": "پلاتر سعی کرد محض احتیاط یک نسخه پشتیبان ذخیره کند، اما موفق نشد. سعی کنید از پلاتر خارج شوید و دوباره آن را راه اندازی کنید."
  },
  "Plottr updated your file without a problem. Don't forget to save your file.": {
    "message": "پلاتر فایل شما را بدون مشکل به روزرسانی کرد. یادتان نرود فایل خود را ذخیره کنید."
  },
  "Plottr verified your license key successfully, but there was an error saving that. Let's try one more time": {
    "message": "پلاتر با موفقیت کلید مجوز شما را تأیید کرد، اما خطایی حین ذخیرۀ آن رخ داد. بیایید یک بار دیگر امتحان کنیم"
  },
  "Problem saving backup": {
    "message": "مشکل در ذخیره پشتیبان"
  },
  "Report a problem": {
    "message": "گزارش یک مشکل"
  },
  "Request a feature": {
    "message": "درخواست یک ویژگی"
  },
  "Reset": {
    "message": "بازنشانی"
  },
  "Save & Close": {
    "message": "ذخیره و بستن"
  },
  "Scene 1": {
    "message": "صحنه ۱"
  },
  "Scene {number}": {
    "message": "صحنه {number}"
  },
  "Scene {number} name": {
    "message": "نام صحنه {number}"
  },
  "Story line name": {
    "message": "نام خط داستان"
  },
  "TRIAL Version": {
    "message": "نسخه آزمایشی"
  },
  "Try again by clicking in the menu: Plottr > Verify License...": {
    "message": "دوباره با کلیک در منو امتحان کنید: پلاتر > تأیید مجوز..."
  },
  "Update Plottr": {
    "message": "به‌روزسانی پلاتر"
  },
  "Upload the file Plottr just exported": {
    "message": "آپلود فایلی که پلاتر هم اکنون صادر کرد"
  },
  "Use the code \"freetrial\" to get the secret discount": {
    "message": "از کد \"freetrial\" برای دریافت تخفیف محرمانه استفاده کنید"
  },
  "Verifying your license. Please wait...": {
    "message": "در حال تأیید مجوز شما. لطفاً منتظر بمانید..."
  },
  "Where would you like to start your new file?": {
    "message": "می‌خواهید فایل جدیدتان را از کجا شروع کنید؟"
  },
  "Would you like to open an existing file or start a new file?": {
    "message": "مایلید یک فایل موجود را باز کنید یا یک فایل جدید آغاز کنید؟"
  },
  "Would you like to save before exiting?": {
    "message": "مایلید قبل از خروج ذخیره کنید؟"
  },
  "You should have received a license key from Gumroad.": {
    "message": "باید یک فایل مجوز از گامرود دریافت کرده باشید."
  },
  "Your free trial has expired!": {
    "message": "نسخه آزمایشی رایگان شما منقضی شده!"
  },
  "a new card": {
    "message": "یک کارت جدید"
  },
  "description": {
    "message": "شرح"
  },
  "learn how": {
    "message": "راهش را یاد بگیرید"
  },
  "name": {
    "message": "نام"
  },
  "New Card": {
    "message": "کارت جدید"
  },
  "new character": {
    "message": "شخصیت جدید"
  },
  "new note": {
    "message": "یادداشت جدید"
  },
  "new place": {
    "message": "مکان جدید"
  },
  "new tag": {
    "message": "برچسب جدید"
  },
  "no, just exit": {
    "message": "نه، فقط خارج شو"
  },
  "no, open the file as-is": {
    "message": "نه، فایل را همانطور که هست باز کن"
  },
  "ok": {
    "message": "تأیید"
  },
  "story line": {
    "message": "خط داستان"
  },
  "tag name": {
    "message": "نام برچسب"
  },
  "title": {
    "message": "عنوان"
  },
  "yes, save!": {
    "message": "بله، ذخیره شود!"
  },
  "yes, update the file": {
    "message": "بله، فایل به روز رسانی شود"
  },
  "{\n      count, plural,\n        one {1 carte}\n        other {# cartes}\n    }": {
    "message": "{\n      شمارش، جمع\n        یک {1 کارت}\n        دیگر {# کارت}\n    }"
  },
  "{\n      count, plural,\n        one {1 note}\n        other {# notes}\n    }": {
    "message": "{\n      شمارش، جمع\n        یک {1 یادداشت}\n        دیگر {# یادداشت}\n    }"
  },
  "{days} days remaining": {
    "message": "{days} روز باقی مانده"
  },
  "Are you sure you want to delete {template}?": {
    "message": "واقعاً می‌خواهید {template} را حذف کنید؟"
  },
  "Character Custom Attributes": {
    "message": "ویژگیهای سفارشی شخصیت"
  },
  "Check for updates": {
    "message": "بررسی به‌روزرسانی‌ها"
  },
  "Checking for updates": {
    "message": "بررسی برای به‌روزرسانی‌ها"
  },
  "Choose an image below or upload a new one": {
    "message": "یک تصویر از زیر انتخاب کنید یا یک تصویر جدید آپلود کنید"
  },
  "Could not display license key. Try again": {
    "message": "کلید مجوز نمایش داده نمی شود. دوباره تلاش کنید"
  },
  "Crafted in the Mountains of Utah": {
    "message": "تولید شده در کوهستان‌های یوتا"
  },
  "Create an error report": {
    "message": "ایجاد یک گزارش خطا"
  },
  "Create unlimited story files": {
    "message": "ایجاد فایلهای داستان نامحدود"
  },
  "Do you want to delete this book: { book }?": {
    "message": "مایلید این کتاب را حذف کنید: { book }؟"
  },
  "Do you want to delete this chapter: { title }?": {
    "message": "مایلید این فصل را حذف کنید: { title }؟"
  },
  "Download Now": {
    "message": "اکنون دانلود شود"
  },
  "Downloading ({percent}%)": {
    "message": "در حال دانلود ({percent}%)"
  },
  "Enter a customer service code": {
    "message": "یک کد خدمات مشتریان وارد کنید"
  },
  "Enter your code": {
    "message": "کد خود را وارد کنید"
  },
  "Error": {
    "message": "خطا"
  },
  "Extending your trial didn't work. Let's try again.": {
    "message": "تمدید نسخه آزمایشی انجام نشد. لطفاً دوباره تلاش کنید."
  },
  "Facebook Support Group": {
    "message": "گروه پشتیبانی فیسبوک"
  },
  "Here is your license key": {
    "message": "کلید مجوز شما اینجاست"
  },
  "New File": {
    "message": "فایل جدید"
  },
  "New from Template": {
    "message": "جدید از قالب"
  },
  "No updates available": {
    "message": "به‌روزرسانی موجود نیست"
  },
  "Open File": {
    "message": "باز کردن فایل"
  },
  "Plottr Trial": {
    "message": "آزمایش پلاتر"
  },
  "Plottr created a file named plottr_error_report.txt in your Documents folder": {
    "message": "پلاتر فایلی به نام plottr_error_report.txt در پوشه اسناد شما ایجاد کرد"
  },
  "Quit and Install": {
    "message": "خروج و نصب"
  },
  "See the Changelog": {
    "message": "مشاهده گزارش تغییر"
  },
  "This is your Device ID": {
    "message": "این شناسه دستگاه شماست"
  },
  "Try that again, but if it keeps happening, use the help menu to create an error report and report the problem.": {
    "message": "دوباره این را امتحان کنید، اما اگر باز هم رخ داد، از منوی راهنما برای ایجاد یک گزارش خطا استفاده کنید و مشکل را گزارش دهید."
  },
  "Update Ready": {
    "message": "به‌روز‌رسانی آماده است"
  },
  "Update available!": {
    "message": "به‌روزرسانی موجود است!"
  },
  "Upload a new image": {
    "message": "آپلود یک تصویر جدید"
  },
  "View Device ID": {
    "message": "مشاهده شناسه دستگاه"
  },
  "View License Key": {
    "message": "مشاهده کلید مجوز"
  },
  "View the Tour": {
    "message": "مشاهده تور"
  },
  "paragraph": {
    "message": "پاراگراف"
  },
  "selected": {
    "message": "انتخاب شده"
  },
  "{\n      count, plural,\n        one {1 card}\n        other {# cards}\n    }": {
    "message": "{\n      شمارش، جمع\n        یک {1 کارت}\n        دیگر {# کارت}\n    }"
  },
  "Import": {
    "message": "وارد کردن"
  },
  "Enter title": {
    "message": "عنوان را وارد کنید"
  },
  "Duplicate": {
    "message": "کپی کردن"
  },
  "(Series View)": {
    "message": "(Series View)"
  },
  "({ thing }).": {
    "message": "({ thing })."
  },
  ".docx": {
    "message": ".docx"
  },
  ".scriv": {
    "message": ".scriv"
  },
  "Access all the features": {
    "message": "Access all the features"
  },
  "Act": {
    "message": "Act"
  },
  "Act Structure": {
    "message": "Act Structure"
  },
  "Action": {
    "message": "Action"
  },
  "Active": {
    "message": "Active"
  },
  "Advanced": {
    "message": "Advanced"
  },
  "Also save backups on this device": {
    "message": "Also save backups on this device"
  },
  "Always Open Dashboard First": {
    "message": "Always Open Dashboard First"
  },
  "Appearance: Dark/Light": {
    "message": "Appearance: Dark/Light"
  },
  "Are you sure you want to deactivate your license key?": {
    "message": "Are you sure you want to deactivate your license key?"
  },
  "Are you sure you want to delete all chapters and their scene cards in \"{beatTitle}\".": {
    "message": "Are you sure you want to delete all chapters and their scene cards in \"{beatTitle}\"."
  },
  "Are you sure you want to delete all scene cards in \"{beatTitle}\".": {
    "message": "Are you sure you want to delete all scene cards in \"{beatTitle}\"."
  },
  "Are you sure you want to remove the {template} template and all its data?": {
    "message": "Are you sure you want to remove the {template} template and all its data?"
  },
  "Are you sure? Removing a level will delete the timeline cards directly under this level's heading cards (from all books across the project).": {
    "message": "Are you sure? Removing a level will delete the timeline cards directly under this level's heading cards (from all books across the project)."
  },
  "At least two levels of hierarchy required to view as tabs": {
    "message": "At least two levels of hierarchy required to view as tabs"
  },
  "Backup Options": {
    "message": "Backup Options"
  },
  "Backups beyond this will be erased": {
    "message": "Backups beyond this will be erased"
  },
  "Beats": {
    "message": "Beats"
  },
  "Beta": {
    "message": "Beta"
  },
  "Black (default)": {
    "message": "Black (default)"
  },
  "Blue (default)": {
    "message": "Blue (default)"
  },
  "Body": {
    "message": "Body"
  },
  "Browser": {
    "message": "Browser"
  },
  "Can't move card to empty book": {
    "message": "Can't move card to empty book"
  },
  "Change book": {
    "message": "Change book"
  },
  "Change color": {
    "message": "Change color"
  },
  "Character Name": {
    "message": "Character Name"
  },
  "Children": {
    "message": "Children"
  },
  "Choose what categories you want to put your notes into": {
    "message": "Choose what categories you want to put your notes into"
  },
  "Choose what categories you want to put your places into": {
    "message": "Choose what categories you want to put your places into"
  },
  "Choose what to upload": {
    "message": "Choose what to upload"
  },
  "Choose your Scrivener project": {
    "message": "Choose your Scrivener project"
  },
  "Choose your backup location": {
    "message": "Choose your backup location"
  },
  "Click here to log in": {
    "message": "Click here to log in"
  },
  "Collaborator": {
    "message": "Collaborator"
  },
  "Colors": {
    "message": "Colors"
  },
  "Comedy": {
    "message": "Comedy"
  },
  "Configure Pro settings": {
    "message": "Configure Pro settings"
  },
  "Confirm Placement": {
    "message": "Confirm Placement"
  },
  "Continue": {
    "message": "Continue"
  },
  "Continue working when your connection goes down.": {
    "message": "Continue working when your connection goes down."
  },
  "Create New Project": {
    "message": "Create New Project"
  },
  "Create unlimited projects": {
    "message": "Create unlimited projects"
  },
  "Dark": {
    "message": "Dark"
  },
  "Days of Backups": {
    "message": "Days of Backups"
  },
  "Deactivate": {
    "message": "Deactivate"
  },
  "Default": {
    "message": "Default"
  },
  "Default Placement": {
    "message": "Default Placement"
  },
  "Delete plotline": {
    "message": "Delete plotline"
  },
  "Disabled": {
    "message": "Disabled"
  },
  "Don't forget to make a backup of your files first.": {
    "message": "Don't forget to make a backup of your files first."
  },
  "Done!": {
    "message": "Done!"
  },
  "Download Complete 🎉 (version {version})": {
    "message": "Download Complete 🎉 (version {version})"
  },
  "Duplicate plotline": {
    "message": "Duplicate plotline"
  },
  "Edit title": {
    "message": "Edit title"
  },
  "Edit {beatName}": {
    "message": "Edit {beatName}"
  },
  "Edit {lineName}": {
    "message": "Edit {lineName}"
  },
  "Enabled": {
    "message": "Enabled"
  },
  "Expand or collapse all stacks": {
    "message": "Expand or collapse all stacks"
  },
  "Expand or collapse stacks": {
    "message": "Expand or collapse stacks"
  },
  "Export to:": {
    "message": "Export to:"
  },
  "Finally, toggle the switch to turn on/off Act Structure.": {
    "message": "Finally, toggle the switch to turn on/off Act Structure."
  },
  "Font Default: Text Editor": {
    "message": "Font Default: Text Editor"
  },
  "From the \"Dashboard\", click \"Settings\" from the side menu.": {
    "message": "From the \"Dashboard\", click \"Settings\" from the side menu."
  },
  "Give Feedback": {
    "message": "Give Feedback"
  },
  "Give this file a new name": {
    "message": "Give this file a new name"
  },
  "Go!": {
    "message": "Go!"
  },
  "Green (default)": {
    "message": "Green (default)"
  },
  "Hides sensitive info for when you are sharing your screen": {
    "message": "Hides sensitive info for when you are sharing your screen"
  },
  "Horror": {
    "message": "Horror"
  },
  "How to turn on Act Structure": {
    "message": "How to turn on Act Structure"
  },
  "I have Plottr Pro": {
    "message": "I have Plottr Pro"
  },
  "I have a<br/>License Key": {
    "message": "I have a<br/>License Key"
  },
  "I'm Done!": {
    "message": "I'm Done!"
  },
  "Import File": {
    "message": "Import File"
  },
  "It doesn't look like you have a pro license.": {
    "message": "It doesn't look like you have a pro license."
  },
  "It looks like you already have an active trial.": {
    "message": "It looks like you already have an active trial."
  },
  "It looks like you've used all your license activations. Manage or upgrade here: <a>My Plottr Account</a>": {
    "message": "It looks like you've used all your license activations. Manage or upgrade here: <a>My Plottr Account</a>"
  },
  "It looks like your version of Plottr is older than this project. Please update Plottr to avoid any issues": {
    "message": "It looks like your version of Plottr is older than this project. Please update Plottr to avoid any issues"
  },
  "Last step": {
    "message": "Last step"
  },
  "Let's set up your Pro account": {
    "message": "Let's set up your Pro account"
  },
  "Levels": {
    "message": "Levels"
  },
  "License Information": {
    "message": "License Information"
  },
  "Light": {
    "message": "Light"
  },
  "Log Out": {
    "message": "Log Out"
  },
  "Move card to { bookTitle }": {
    "message": "Move card to { bookTitle }"
  },
  "Move plotline": {
    "message": "Move plotline"
  },
  "Mystery": {
    "message": "Mystery"
  },
  "Name Your Project:": {
    "message": "Name Your Project:"
  },
  "No Matches": {
    "message": "No Matches"
  },
  "No files found.": {
    "message": "No files found."
  },
  "None": {
    "message": "None"
  },
  "Not Active": {
    "message": "Not Active"
  },
  "Not Now": {
    "message": "Not Now"
  },
  "Note Categories": {
    "message": "Note Categories"
  },
  "Note Title": {
    "message": "Note Title"
  },
  "Offline": {
    "message": "Offline"
  },
  "Offline Mode": {
    "message": "Offline Mode"
  },
  "Ok": {
    "message": "Ok"
  },
  "On the \"Settings\" modal, click on the \"Beta\" tab.": {
    "message": "On the \"Settings\" modal, click on the \"Beta\" tab."
  },
  "On the top right corner of the app, click the \"Dashboard\" button.": {
    "message": "On the top right corner of the app, click the \"Dashboard\" button."
  },
  "Orange (default)": {
    "message": "Orange (default)"
  },
  "Organize your scene cards into Chapters and Acts": {
    "message": "Organize your scene cards into Chapters and Acts"
  },
  "Owner": {
    "message": "Owner"
  },
  "Permission": {
    "message": "Permission"
  },
  "Place Categories": {
    "message": "Place Categories"
  },
  "Place Name": {
    "message": "Place Name"
  },
  "Playwriting": {
    "message": "Playwriting"
  },
  "Plottr created a file named {filePath} in your Documents folder": {
    "message": "Plottr created a file named {filePath} in your Documents folder"
  },
  "Plottr opens your most recent project at start": {
    "message": "Plottr opens your most recent project at start"
  },
  "Plottr ran into a problem and can't start.  Please contact support.": {
    "message": "Plottr ran into a problem and can't start.  Please contact support."
  },
  "Plottr ran into an issue opening your project. Please check your backups or contact support about this project and we will get it running for you quickly.": {
    "message": "Plottr ran into an issue opening your project. Please check your backups or contact support about this project and we will get it running for you quickly."
  },
  "Plottr ran into an issue opening your project. Please check your backups or contact support with this file and we will get it running for you quickly.": {
    "message": "Plottr ran into an issue opening your project. Please check your backups or contact support with this file and we will get it running for you quickly."
  },
  "Preview:": {
    "message": "Preview:"
  },
  "Pro Subscription": {
    "message": "Pro Subscription"
  },
  "Product Name": {
    "message": "Product Name"
  },
  "Projects": {
    "message": "Projects"
  },
  "Put Description in:": {
    "message": "Put Description in:"
  },
  "Red (default)": {
    "message": "Red (default)"
  },
  "Requires you to restart plottr": {
    "message": "Requires you to restart plottr"
  },
  "Restore Default": {
    "message": "Restore Default"
  },
  "Restore Defaults": {
    "message": "Restore Defaults"
  },
  "Romance": {
    "message": "Romance"
  },
  "Save and Open": {
    "message": "Save and Open"
  },
  "Save backups on this device": {
    "message": "Save backups on this device"
  },
  "Save backups to this device as well as in the cloud": {
    "message": "Save backups to this device as well as in the cloud"
  },
  "Saved in the Cloud": {
    "message": "Saved in the Cloud"
  },
  "Saving worked this time 🎉": {
    "message": "Saving worked this time 🎉"
  },
  "Screenplay": {
    "message": "Screenplay"
  },
  "Scrivener file": {
    "message": "Scrivener file"
  },
  "Search Documentation": {
    "message": "Search Documentation"
  },
  "See? That was painless 😁": {
    "message": "See? That was painless 😁"
  },
  "Short Story": {
    "message": "Short Story"
  },
  "Show File": {
    "message": "Show File"
  },
  "Sign in": {
    "message": "Sign in"
  },
  "Sign in with your my.plottr.com account": {
    "message": "Sign in with your my.plottr.com account"
  },
  "Snowflake Pro": {
    "message": "Snowflake Pro"
  },
  "Spell Check": {
    "message": "Spell Check"
  },
  "Stacked": {
    "message": "Stacked"
  },
  "Start Plottr Pro": {
    "message": "Start Plottr Pro"
  },
  "Start the<br/>Free Trial": {
    "message": "Start the<br/>Free Trial"
  },
  "Status": {
    "message": "Status"
  },
  "Step {number}": {
    "message": "Step {number}"
  },
  "Streaming Friendly": {
    "message": "Streaming Friendly"
  },
  "Stress test saving": {
    "message": "Stress test saving"
  },
  "Structure": {
    "message": "Structure"
  },
  "Successfully resumed.": {
    "message": "Successfully resumed."
  },
  "Synopsis": {
    "message": "Synopsis"
  },
  "System": {
    "message": "System"
  },
  "Tabbed": {
    "message": "Tabbed"
  },
  "Take Control": {
    "message": "Take Control"
  },
  "Template": {
    "message": "Template"
  },
  "Testing utilities": {
    "message": "Testing utilities"
  },
  "The cloud file is different from your local copy.  We created a duplicate of your local file and switched to the cloud file.": {
    "message": "The cloud file is different from your local copy.  We created a duplicate of your local file and switched to the cloud file."
  },
  "There was an error doing that. Try again.": {
    "message": "There was an error doing that. Try again."
  },
  "There was an error reconnecting.  Please save the file and restart Plottr.": {
    "message": "There was an error reconnecting.  Please save the file and restart Plottr."
  },
  "There was an error uploading your offline backup. Please exit and start again": {
    "message": "There was an error uploading your offline backup. Please exit and start again"
  },
  "This appears to be a Plottr Pro file.  Please log in.": {
    "message": "This appears to be a Plottr Pro file.  Please log in."
  },
  "This will be quick and painless. There are only 3 steps:": {
    "message": "This will be quick and painless. There are only 3 steps:"
  },
  "Timeline Structure": {
    "message": "Timeline Structure"
  },
  "To give feedback on this feature, please visit:": {
    "message": "To give feedback on this feature, please visit:"
  },
  "To use \"{ thing }\" in Plottr Pro, you need to upload it first.": {
    "message": "To use \"{ thing }\" in Plottr Pro, you need to upload it first."
  },
  "Update Available 🎉 (version {version})": {
    "message": "Update Available 🎉 (version {version})"
  },
  "Update failed. <b>Try again</b> or <a>install manually</a>": {
    "message": "Update failed. <b>Try again</b> or <a>install manually</a>"
  },
  "Upload": {
    "message": "Upload"
  },
  "Upload ALL projects & templates": {
    "message": "Upload ALL projects & templates"
  },
  "Upload Existing Project": {
    "message": "Upload Existing Project"
  },
  "Upload to Plottr Pro?": {
    "message": "Upload to Plottr Pro?"
  },
  "Upload your projects and templates": {
    "message": "Upload your projects and templates"
  },
  "Uploading": {
    "message": "Uploading"
  },
  "Uploading...": {
    "message": "Uploading..."
  },
  "View Backups": {
    "message": "View Backups"
  },
  "View timeline ith tabs for the highest level": {
    "message": "View timeline ith tabs for the highest level"
  },
  "Viewer": {
    "message": "Viewer"
  },
  "We couldn't find a Pro account with that email": {
    "message": "We couldn't find a Pro account with that email"
  },
  "We ran into problems uploading some files": {
    "message": "We ran into problems uploading some files"
  },
  "Welcome to Plottr Pro": {
    "message": "Welcome to Plottr Pro"
  },
  "When Plottr opens, the first thing you'll see is the dashboard": {
    "message": "When Plottr opens, the first thing you'll see is the dashboard"
  },
  "White (default)": {
    "message": "White (default)"
  },
  "Woohoo! Scene card duplicated": {
    "message": "Woohoo! Scene card duplicated"
  },
  "Wrong file format": {
    "message": "Wrong file format"
  },
  "Yellow (default)": {
    "message": "Yellow (default)"
  },
  "You can always change these later": {
    "message": "You can always change these later"
  },
  "You need to update Plottr": {
    "message": "You need to update Plottr"
  },
  "Your changes were uploaded to the cloud.": {
    "message": "Your changes were uploaded to the cloud."
  },
  "but don't panic, you haven't lost anything": {
    "message": "but don't panic, you haven't lost anything"
  },
  "last edited": {
    "message": "last edited"
  },
  "plottr.com/beta": {
    "message": "plottr.com/beta"
  },
  "{type} template": {
    "message": "{type} template"
  },
  "Add Scene": {
    "message": "Add Scene"
  },
  "Add Another Scene": {
    "message": "Add Another Scene"
  },
  "Congratulations": {
    "message": "Congratulations"
  },
  "Delete Book": {
    "message": "Delete Book"
  },
  "Delete Book {name}?": {
    "message": "Delete Book {name}?"
  },
  "Delete Chapter?": {
    "message": "Delete Chapter?"
  },
  "Do you want to delete tag {name}?": {
    "message": "Do you want to delete tag {name}?"
  },
  "Editor is currently locked by {name}.": {
    "message": "Editor is currently locked by {name}."
  },
  "example@domain.com": {
    "message": "example@domain.com"
  },
  "Error sharing file": {
    "message": "Error sharing file"
  },
  "From File": {
    "message": "From File"
  },
  "From Template": {
    "message": "From Template"
  },
  "Hey, check out my Plottr project \"{project}\"": {
    "message": "Hey, check out my Plottr project \"{project}\""
  },
  "Hold On!": {
    "message": "Hold On!"
  },
  "Let's get you started": {
    "message": "Let's get you started"
  },
  "Manage the Categories you wish to place your characters in.": {
    "message": "Manage the Categories you wish to place your characters in."
  },
  "No Documents Found": {
    "message": "No Documents Found"
  },
  "NOT NOW": {
    "message": "NOT NOW"
  },
  "Please verify your license in {time}": {
    "message": "Please verify your license in {time}"
  },
  "PLOTTR PRO": {
    "message": "PLOTTR PRO"
  },
  "PLOTTR CLASSIC": {
    "message": "PLOTTR CLASSIC"
  },
  "Purchase Pro": {
    "message": "Purchase Pro"
  },
  "Save as\nTemplate": {
    "message": "Save as\nTemplate"
  },
  "See More": {
    "message": "See More"
  },
  "See Less": {
    "message": "See Less"
  },
  "See that was painless": {
    "message": "See that was painless"
  },
  "Start": {
    "message": "Start"
  },
  "Plottr Pro Wizard": {
    "message": "Plottr Pro Wizard"
  },
  "START PLOTTING": {
    "message": "START PLOTTING"
  },
  "There was an error while sharing your file. Try Again.": {
    "message": "There was an error while sharing your file. Try Again."
  },
  "There was an error trying to sign you in. Ensure you password and email are correct.": {
    "message": "There was an error trying to sign you in. Ensure you password and email are correct."
  },
  "This will be quick and painless.": {
    "message": "This will be quick and painless."
  },
  "There are only ": {
    "message": "There are only "
  },
  "{number} steps:": {
    "message": "{number} steps:"
  },
  "Try Plottr Pro today for a seamless cloud experience like you have never imagined.": {
    "message": "Try Plottr Pro today for a seamless cloud experience like you have never imagined."
  },
  "Unknown": {
    "message": "Unknown"
  },
  "Upload projects and templates": {
    "message": "Upload projects and templates"
  },
  "Uploading projects and templates": {
    "message": "Uploading projects and templates"
  },
  "UPLOADING...": {
    "message": "UPLOADING..."
  },
  "Upload Projects": {
    "message": "Upload Projects"
  },
  "Use Book\nTemplate": {
    "message": "Use Book\nTemplate"
  },
  "Use Scene\nTemplate": {
    "message": "Use Scene\nTemplate"
  },
  "Use License Code Login": {
    "message": "Use License Code Login"
  },
  "Use Plottr Pro Login": {
    "message": "Use Plottr Pro Login"
  },
  "You cannot delete the last chapter.": {
    "message": "You cannot delete the last chapter."
  },
  "You cannot delete the last plotline.": {
    "message": "You cannot delete the last plotline."
  },
  "You have no {type}s": {
    "message": "You have no {type}s"
  },
  "You need to have an active Plottr Pro account to continue": {
    "message": "You need to have an active Plottr Pro account to continue"
  },
  "You currently have no available licenses for this email.": {
    "message": "You currently have no available licenses for this email."
  },
  "Your next great plot begins with Plottr.": {
    "message": "Your next great plot begins with Plottr."
  },
  "Character's Categories": {
    "message": "Character's Categories"
  },
  "Checking licenses for {email}": {
    "message": "Checking licenses for {email}"
  },
  "No more {type}s": {
    "message": "No more {type}s"
  },
  "Auto Number": {
    "message": "Auto Number"
  },
  "Auto-Save": {
    "message": "Auto-Save"
  },
  "Use Templates": {
    "message": "Use Templates"
  },
  "On the top right corner of the app, click the 'Dashboard' button.": {
    "message": "On the top right corner of the app, click the 'Dashboard' button."
  },
  "From the 'Dashboard', click 'Settings' from the side menu.": {
    "message": "From the 'Dashboard', click 'Settings' from the side menu."
  },
  "On the 'Settings' modal, click on the 'Beta tab.": {
    "message": "On the 'Settings' modal, click on the 'Beta tab."
  },
  "Woohoo! Scene card moved to": {
    "message": "Woohoo! Scene card moved to"
  },
  "Sharing": {
    "message": "Sharing"
  },
  "Send Invite": {
    "message": "Send Invite"
  },
  "Email Address": {
    "message": "Email Address"
  },
  "Permissions": {
    "message": "Permissions"
  },
  "Download": {
    "message": "Download"
  },
  "Import from Snowflake Pro": {
    "message": "Import from Snowflake Pro"
  },
  "See What’s New": {
    "message": "See What’s New"
  },
  "About": {
    "message": "About"
  },
  "Beta Information": {
    "message": "Beta Information"
  },
  "Beta Email": {
    "message": "Beta Email"
  },
  "Admin": {
    "message": "Admin"
  },
  "Remove Pro on this Device": {
    "message": "Remove Pro on this Device"
  },
  "Use this if you logged into Pro by accident": {
    "message": "Use this if you logged into Pro by accident"
  },
  "Are you sure you want to delete {plotline}?": {
    "message": "Are you sure you want to delete {plotline}?"
  },
  "Are you sure you want to delete {chapter #}?": {
    "message": "Are you sure you want to delete {chapter #}?"
  },
  "Custom Attributes For Scenes": {
    "message": "Custom Attributes For Scenes"
  },
  "Choose what you want to track about your scenes": {
    "message": "Choose what you want to track about your scenes"
  },
  "Edit New Plotline": {
    "message": "Edit New Plotline"
  },
  "Timeline Settings": {
    "message": "Timeline Settings"
  },
  "Dashed": {
    "message": "Dashed"
  },
  "Solid": {
    "message": "Solid"
  },
  "Dotted": {
    "message": "Dotted"
  },
  "Enter some text…": {
    "message": "Enter some text…"
  },
  "Custom Attributes For Characters": {
    "message": "Custom Attributes For Characters"
  },
  "text": {
    "message": "text"
  },
  "Custom Attributes For Places": {
    "message": "Custom Attributes For Places"
  },
  "App Version: { version }": {
    "message": "App Version: { version }"
  },
  "{\n count, plural,\n one {1 place attached}\n  other {# places attached}\n }": {
    "message": "{\n count, plural,\n one {1 place attached}\n  other {# places attached}\n }"
  },
  "{\n count, plural,\n one {1 tag attached}\n other {# tags attached}\n }": {
    "message": "{\n count, plural,\n one {1 tag attached}\n other {# tags attached}\n }"
  },
  "{\n count, plural,\n one {1 card}\n other {# card}\n}": {
    "message": "{\n count, plural,\n one {1 card}\n other {# card}\n}"
  },
  "{\n count, plural,\n one {1 note}\n other {# notes}\n}": {
    "message": "{\n count, plural,\n one {1 note}\n other {# notes}\n}"
  },
  "Please contact me with any questions at support@plottr.com": {
    "message": "Please contact me with any questions at support@plottr.com"
  },
  "{\n count, plural,\n one {1 character attached}\n other {# characters attached}\n        }": {
    "message": "{\n count, plural,\n one {1 character attached}\n other {# characters attached}\n        }"
  },
  "{\n      count, plural,\n        one {1 card}\n        other {# card}\n    }": {
    "message": "{\n      count, plural,\n        one {1 card}\n        other {# card}\n    }"
  },
  "{\n count, plural,\n one {1 place attached}\n other {# places attached}\n }": {
    "message": "{\n count, plural,\n one {1 place attached}\n other {# places attached}\n }"
  },
  "{\n count, plural,\n one {1 tag attached}\n other {# tags attached}\n}": {
    "message": "{\n count, plural,\n one {1 tag attached}\n other {# tags attached}\n}"
  },
  "Filter by storyline": {
    "message": "Filter by storyline"
  },
  "Could not display the license key. Try again": {
    "message": "Could not display the license key. Try again"
  }
}